byted_project_oapi_sdk/__init__.py
byted_project_oapi_sdk-0.0.1.dist-info/METADATA
byted_project_oapi_sdk-0.0.1.dist-info/WHEEL
byted_project_oapi_sdk-0.0.1.dist-info/top_level.txt
byted_project_oapi_sdk-0.0.1.dist-info/RECORD
