Metadata-Version: 2.1
Name: byted-project-oapi-sdk
Version: 0.0.1
Summary: A simple package named byted_project_oapi_sdk
Home-page: https://github.com/artifact/byted_project_oapi_sdk.git
Author: artifact
Author-email: artifact@example.com
License: UNKNOWN
Platform: UNKNOWN
Classifier: Programming Language :: Python :: 3
Classifier: License :: OSI Approved :: MIT License
Classifier: Operating System :: OS Independent
